{
    "CrossLanguagePackageId": "Microsoft.NetApp",
    "CrossLanguageDefinitionId": {
        "azure.mgmt.netapp.models.AccountEncryption": "Microsoft.NetApp.AccountEncryption",
        "azure.mgmt.netapp.models.AccountProperties": "Microsoft.NetApp.AccountProperties",
        "azure.mgmt.netapp.models.ActiveDirectory": "Microsoft.NetApp.ActiveDirectory",
        "azure.mgmt.netapp.models.AuthorizeRequest": "Microsoft.NetApp.AuthorizeRequest",
        "azure.mgmt.netapp.models.Resource": "Azure.ResourceManager.CommonTypes.Resource",
        "azure.mgmt.netapp.models.ProxyResource": "Azure.ResourceManager.CommonTypes.ProxyResource",
        "azure.mgmt.netapp.models.Backup": "Microsoft.NetApp.Backup",
        "azure.mgmt.netapp.models.BackupPatch": "Microsoft.NetApp.BackupPatch",
        "azure.mgmt.netapp.models.BackupPatchProperties": "Microsoft.NetApp.BackupPatchProperties",
        "azure.mgmt.netapp.models.TrackedResource": "Azure.ResourceManager.CommonTypes.TrackedResource",
        "azure.mgmt.netapp.models.BackupPolicy": "Microsoft.NetApp.BackupPolicy",
        "azure.mgmt.netapp.models.BackupPolicyPatch": "Microsoft.NetApp.BackupPolicyPatch",
        "azure.mgmt.netapp.models.BackupPolicyProperties": "Microsoft.NetApp.BackupPolicyProperties",
        "azure.mgmt.netapp.models.BackupProperties": "Microsoft.NetApp.BackupProperties",
        "azure.mgmt.netapp.models.BackupRestoreFiles": "Microsoft.NetApp.BackupRestoreFiles",
        "azure.mgmt.netapp.models.BackupsMigrationRequest": "Microsoft.NetApp.BackupsMigrationRequest",
        "azure.mgmt.netapp.models.BackupStatus": "Microsoft.NetApp.BackupStatus",
        "azure.mgmt.netapp.models.BackupVault": "Microsoft.NetApp.BackupVault",
        "azure.mgmt.netapp.models.BackupVaultPatch": "Microsoft.NetApp.BackupVaultPatch",
        "azure.mgmt.netapp.models.BackupVaultProperties": "Microsoft.NetApp.BackupVaultProperties",
        "azure.mgmt.netapp.models.BreakFileLocksRequest": "Microsoft.NetApp.BreakFileLocksRequest",
        "azure.mgmt.netapp.models.BreakReplicationRequest": "Microsoft.NetApp.BreakReplicationRequest",
        "azure.mgmt.netapp.models.Bucket": "Microsoft.NetApp.Bucket",
        "azure.mgmt.netapp.models.BucketCredentialsExpiry": "Microsoft.NetApp.BucketCredentialsExpiry",
        "azure.mgmt.netapp.models.BucketGenerateCredentials": "Microsoft.NetApp.BucketGenerateCredentials",
        "azure.mgmt.netapp.models.BucketPatch": "Microsoft.NetApp.BucketPatch",
        "azure.mgmt.netapp.models.BucketPatchProperties": "Microsoft.NetApp.BucketPatchProperties",
        "azure.mgmt.netapp.models.BucketProperties": "Microsoft.NetApp.BucketProperties",
        "azure.mgmt.netapp.models.BucketServerPatchProperties": "Microsoft.NetApp.BucketServerPatchProperties",
        "azure.mgmt.netapp.models.BucketServerProperties": "Microsoft.NetApp.BucketServerProperties",
        "azure.mgmt.netapp.models.CapacityPool": "Microsoft.NetApp.CapacityPool",
        "azure.mgmt.netapp.models.CapacityPoolPatch": "Microsoft.NetApp.CapacityPoolPatch",
        "azure.mgmt.netapp.models.ChangeKeyVault": "Microsoft.NetApp.ChangeKeyVault",
        "azure.mgmt.netapp.models.CheckAvailabilityResponse": "Microsoft.NetApp.CheckAvailabilityResponse",
        "azure.mgmt.netapp.models.CifsUser": "Microsoft.NetApp.CifsUser",
        "azure.mgmt.netapp.models.ClusterPeerCommandResponse": "Microsoft.NetApp.ClusterPeerCommandResponse",
        "azure.mgmt.netapp.models.DailySchedule": "Microsoft.NetApp.DailySchedule",
        "azure.mgmt.netapp.models.DestinationReplication": "Microsoft.NetApp.DestinationReplication",
        "azure.mgmt.netapp.models.Dimension": "Microsoft.NetApp.Dimension",
        "azure.mgmt.netapp.models.EncryptionIdentity": "Microsoft.NetApp.EncryptionIdentity",
        "azure.mgmt.netapp.models.EncryptionTransitionRequest": "Microsoft.NetApp.EncryptionTransitionRequest",
        "azure.mgmt.netapp.models.ErrorAdditionalInfo": "Azure.ResourceManager.CommonTypes.ErrorAdditionalInfo",
        "azure.mgmt.netapp.models.ErrorDetail": "Azure.ResourceManager.CommonTypes.ErrorDetail",
        "azure.mgmt.netapp.models.ErrorResponse": "Azure.ResourceManager.CommonTypes.ErrorResponse",
        "azure.mgmt.netapp.models.ExportPolicyRule": "Microsoft.NetApp.ExportPolicyRule",
        "azure.mgmt.netapp.models.FilePathAvailabilityRequest": "Microsoft.NetApp.FilePathAvailabilityRequest",
        "azure.mgmt.netapp.models.FileSystemUser": "Microsoft.NetApp.FileSystemUser",
        "azure.mgmt.netapp.models.GetGroupIdListForLDAPUserRequest": "Microsoft.NetApp.GetGroupIdListForLdapUserRequest",
        "azure.mgmt.netapp.models.GetGroupIdListForLDAPUserResponse": "Microsoft.NetApp.GetGroupIdListForLdapUserResponse",
        "azure.mgmt.netapp.models.GetKeyVaultStatusResponse": "Microsoft.NetApp.GetKeyVaultStatusResponse",
        "azure.mgmt.netapp.models.GetKeyVaultStatusResponseProperties": "Microsoft.NetApp.GetKeyVaultStatusResponseProperties",
        "azure.mgmt.netapp.models.HourlySchedule": "Microsoft.NetApp.HourlySchedule",
        "azure.mgmt.netapp.models.KeyVaultPrivateEndpoint": "Microsoft.NetApp.KeyVaultPrivateEndpoint",
        "azure.mgmt.netapp.models.KeyVaultProperties": "Microsoft.NetApp.KeyVaultProperties",
        "azure.mgmt.netapp.models.LdapConfiguration": "Microsoft.NetApp.LdapConfiguration",
        "azure.mgmt.netapp.models.LdapSearchScopeOpt": "Microsoft.NetApp.LdapSearchScopeOpt",
        "azure.mgmt.netapp.models.ListQuotaReportResponse": "Microsoft.NetApp.ListQuotaReportResponse",
        "azure.mgmt.netapp.models.LogSpecification": "Microsoft.NetApp.LogSpecification",
        "azure.mgmt.netapp.models.ManagedServiceIdentity": "Azure.ResourceManager.CommonTypes.ManagedServiceIdentity",
        "azure.mgmt.netapp.models.MetricSpecification": "Microsoft.NetApp.MetricSpecification",
        "azure.mgmt.netapp.models.MonthlySchedule": "Microsoft.NetApp.MonthlySchedule",
        "azure.mgmt.netapp.models.MountTargetProperties": "Microsoft.NetApp.MountTargetProperties",
        "azure.mgmt.netapp.models.NetAppAccount": "Microsoft.NetApp.NetAppAccount",
        "azure.mgmt.netapp.models.NetAppAccountPatch": "Microsoft.NetApp.NetAppAccountPatch",
        "azure.mgmt.netapp.models.NetworkSiblingSet": "Microsoft.NetApp.NetworkSiblingSet",
        "azure.mgmt.netapp.models.NfsUser": "Microsoft.NetApp.NfsUser",
        "azure.mgmt.netapp.models.NicInfo": "Microsoft.NetApp.NicInfo",
        "azure.mgmt.netapp.models.Operation": "Microsoft.NetApp.Operation",
        "azure.mgmt.netapp.models.OperationDisplay": "Microsoft.NetApp.OperationDisplay",
        "azure.mgmt.netapp.models.OperationProperties": "Microsoft.NetApp.OperationProperties",
        "azure.mgmt.netapp.models.PeerClusterForVolumeMigrationRequest": "Microsoft.NetApp.PeerClusterForVolumeMigrationRequest",
        "azure.mgmt.netapp.models.PlacementKeyValuePairs": "Microsoft.NetApp.PlacementKeyValuePairs",
        "azure.mgmt.netapp.models.PoolChangeRequest": "Microsoft.NetApp.PoolChangeRequest",
        "azure.mgmt.netapp.models.PoolPatchProperties": "Microsoft.NetApp.PoolPatchProperties",
        "azure.mgmt.netapp.models.PoolProperties": "Microsoft.NetApp.PoolProperties",
        "azure.mgmt.netapp.models.QueryNetworkSiblingSetRequest": "Microsoft.NetApp.QueryNetworkSiblingSetRequest",
        "azure.mgmt.netapp.models.QuotaAvailabilityRequest": "Microsoft.NetApp.QuotaAvailabilityRequest",
        "azure.mgmt.netapp.models.QuotaItem": "Microsoft.NetApp.QuotaItem",
        "azure.mgmt.netapp.models.QuotaItemProperties": "Microsoft.NetApp.QuotaItemProperties",
        "azure.mgmt.netapp.models.QuotaReport": "Microsoft.NetApp.QuotaReport",
        "azure.mgmt.netapp.models.ReestablishReplicationRequest": "Microsoft.NetApp.ReestablishReplicationRequest",
        "azure.mgmt.netapp.models.RegionInfo": "Microsoft.NetApp.RegionInfo",
        "azure.mgmt.netapp.models.RegionInfoAvailabilityZoneMappingsItem": "Microsoft.NetApp.RegionInfoAvailabilityZoneMappingsItem",
        "azure.mgmt.netapp.models.RegionInfoResource": "Microsoft.NetApp.RegionInfoResource",
        "azure.mgmt.netapp.models.RelocateVolumeRequest": "Microsoft.NetApp.RelocateVolumeRequest",
        "azure.mgmt.netapp.models.RemotePath": "Microsoft.NetApp.RemotePath",
        "azure.mgmt.netapp.models.Replication": "Microsoft.NetApp.Replication",
        "azure.mgmt.netapp.models.ReplicationObject": "Microsoft.NetApp.ReplicationObject",
        "azure.mgmt.netapp.models.ReplicationStatus": "Microsoft.NetApp.ReplicationStatus",
        "azure.mgmt.netapp.models.ResourceNameAvailabilityRequest": "Microsoft.NetApp.ResourceNameAvailabilityRequest",
        "azure.mgmt.netapp.models.RestoreStatus": "Microsoft.NetApp.RestoreStatus",
        "azure.mgmt.netapp.models.ServiceSpecification": "Microsoft.NetApp.ServiceSpecification",
        "azure.mgmt.netapp.models.Snapshot": "Microsoft.NetApp.Snapshot",
        "azure.mgmt.netapp.models.SnapshotPatch": "Microsoft.NetApp.SnapshotPatch",
        "azure.mgmt.netapp.models.SnapshotPolicy": "Microsoft.NetApp.SnapshotPolicy",
        "azure.mgmt.netapp.models.SnapshotPolicyPatch": "Microsoft.NetApp.SnapshotPolicyPatch",
        "azure.mgmt.netapp.models.SnapshotPolicyProperties": "Microsoft.NetApp.SnapshotPolicyProperties",
        "azure.mgmt.netapp.models.SnapshotPolicyVolumeList": "Microsoft.NetApp.SnapshotPolicyVolumeList",
        "azure.mgmt.netapp.models.SnapshotProperties": "Microsoft.NetApp.SnapshotProperties",
        "azure.mgmt.netapp.models.SnapshotRestoreFiles": "Microsoft.NetApp.SnapshotRestoreFiles",
        "azure.mgmt.netapp.models.SubvolumeInfo": "Microsoft.NetApp.SubvolumeInfo",
        "azure.mgmt.netapp.models.SubvolumeModel": "Microsoft.NetApp.SubvolumeModel",
        "azure.mgmt.netapp.models.SubvolumeModelProperties": "Microsoft.NetApp.SubvolumeModelProperties",
        "azure.mgmt.netapp.models.SubvolumePatchParams": "Microsoft.NetApp.SubvolumePatchParams",
        "azure.mgmt.netapp.models.SubvolumePatchRequest": "Microsoft.NetApp.SubvolumePatchRequest",
        "azure.mgmt.netapp.models.SubvolumeProperties": "Microsoft.NetApp.SubvolumeProperties",
        "azure.mgmt.netapp.models.SvmPeerCommandResponse": "Microsoft.NetApp.SvmPeerCommandResponse",
        "azure.mgmt.netapp.models.SystemData": "Azure.ResourceManager.CommonTypes.SystemData",
        "azure.mgmt.netapp.models.UpdateNetworkSiblingSetRequest": "Microsoft.NetApp.UpdateNetworkSiblingSetRequest",
        "azure.mgmt.netapp.models.UsageName": "Microsoft.NetApp.UsageName",
        "azure.mgmt.netapp.models.UsageProperties": "Microsoft.NetApp.UsageProperties",
        "azure.mgmt.netapp.models.UsageResult": "Microsoft.NetApp.UsageResult",
        "azure.mgmt.netapp.models.UserAssignedIdentity": "Azure.ResourceManager.CommonTypes.UserAssignedIdentity",
        "azure.mgmt.netapp.models.Volume": "Microsoft.NetApp.Volume",
        "azure.mgmt.netapp.models.VolumeBackupProperties": "Microsoft.NetApp.VolumeBackupProperties",
        "azure.mgmt.netapp.models.VolumeBackups": "Microsoft.NetApp.VolumeBackups",
        "azure.mgmt.netapp.models.VolumeGroup": "Microsoft.NetApp.VolumeGroup",
        "azure.mgmt.netapp.models.VolumeGroupDetails": "Microsoft.NetApp.VolumeGroupDetails",
        "azure.mgmt.netapp.models.VolumeGroupListProperties": "Microsoft.NetApp.VolumeGroupListProperties",
        "azure.mgmt.netapp.models.VolumeGroupMetaData": "Microsoft.NetApp.VolumeGroupMetaData",
        "azure.mgmt.netapp.models.VolumeGroupProperties": "Microsoft.NetApp.VolumeGroupProperties",
        "azure.mgmt.netapp.models.VolumeGroupVolumeProperties": "Microsoft.NetApp.VolumeGroupVolumeProperties",
        "azure.mgmt.netapp.models.VolumePatch": "Microsoft.NetApp.VolumePatch",
        "azure.mgmt.netapp.models.VolumePatchProperties": "Microsoft.NetApp.VolumePatchProperties",
        "azure.mgmt.netapp.models.VolumePatchPropertiesDataProtection": "Microsoft.NetApp.VolumePatchPropertiesDataProtection",
        "azure.mgmt.netapp.models.VolumePatchPropertiesExportPolicy": "Microsoft.NetApp.VolumePatchPropertiesExportPolicy",
        "azure.mgmt.netapp.models.VolumeProperties": "Microsoft.NetApp.VolumeProperties",
        "azure.mgmt.netapp.models.VolumePropertiesDataProtection": "Microsoft.NetApp.VolumePropertiesDataProtection",
        "azure.mgmt.netapp.models.VolumePropertiesExportPolicy": "Microsoft.NetApp.VolumePropertiesExportPolicy",
        "azure.mgmt.netapp.models.VolumeQuotaRule": "Microsoft.NetApp.VolumeQuotaRule",
        "azure.mgmt.netapp.models.VolumeQuotaRulePatch": "Microsoft.NetApp.VolumeQuotaRulePatch",
        "azure.mgmt.netapp.models.VolumeQuotaRulesProperties": "Microsoft.NetApp.VolumeQuotaRulesProperties",
        "azure.mgmt.netapp.models.VolumeRelocationProperties": "Microsoft.NetApp.VolumeRelocationProperties",
        "azure.mgmt.netapp.models.VolumeRevert": "Microsoft.NetApp.VolumeRevert",
        "azure.mgmt.netapp.models.VolumeSnapshotProperties": "Microsoft.NetApp.VolumeSnapshotProperties",
        "azure.mgmt.netapp.models.WeeklySchedule": "Microsoft.NetApp.WeeklySchedule",
        "azure.mgmt.netapp.models.MetricAggregationType": "Microsoft.NetApp.MetricAggregationType",
        "azure.mgmt.netapp.models.CreatedByType": "Azure.ResourceManager.CommonTypes.createdByType",
        "azure.mgmt.netapp.models.ApplicationType": "Microsoft.NetApp.ApplicationType",
        "azure.mgmt.netapp.models.ServiceLevel": "Microsoft.NetApp.ServiceLevel",
        "azure.mgmt.netapp.models.ChownMode": "Microsoft.NetApp.ChownMode",
        "azure.mgmt.netapp.models.NetworkFeatures": "Microsoft.NetApp.NetworkFeatures",
        "azure.mgmt.netapp.models.VolumeStorageToNetworkProximity": "Microsoft.NetApp.VolumeStorageToNetworkProximity",
        "azure.mgmt.netapp.models.EndpointType": "Microsoft.NetApp.EndpointType",
        "azure.mgmt.netapp.models.ReplicationSchedule": "Microsoft.NetApp.ReplicationSchedule",
        "azure.mgmt.netapp.models.ReplicationType": "Microsoft.NetApp.ReplicationType",
        "azure.mgmt.netapp.models.ExternalReplicationSetupStatus": "Microsoft.NetApp.ExternalReplicationSetupStatus",
        "azure.mgmt.netapp.models.MirrorState": "Microsoft.NetApp.MirrorState",
        "azure.mgmt.netapp.models.VolumeReplicationRelationshipStatus": "Microsoft.NetApp.VolumeReplicationRelationshipStatus",
        "azure.mgmt.netapp.models.AcceptGrowCapacityPoolForShortTermCloneSplit": "Microsoft.NetApp.AcceptGrowCapacityPoolForShortTermCloneSplit",
        "azure.mgmt.netapp.models.SecurityStyle": "Microsoft.NetApp.SecurityStyle",
        "azure.mgmt.netapp.models.SmbAccessBasedEnumeration": "Microsoft.NetApp.SmbAccessBasedEnumeration",
        "azure.mgmt.netapp.models.SmbNonBrowsable": "Microsoft.NetApp.SmbNonBrowsable",
        "azure.mgmt.netapp.models.EncryptionKeySource": "Microsoft.NetApp.EncryptionKeySource",
        "azure.mgmt.netapp.models.LdapServerType": "Microsoft.NetApp.LdapServerType",
        "azure.mgmt.netapp.models.CoolAccessRetrievalPolicy": "Microsoft.NetApp.CoolAccessRetrievalPolicy",
        "azure.mgmt.netapp.models.CoolAccessTieringPolicy": "Microsoft.NetApp.CoolAccessTieringPolicy",
        "azure.mgmt.netapp.models.FileAccessLogs": "Microsoft.NetApp.FileAccessLogs",
        "azure.mgmt.netapp.models.AvsDataStore": "Microsoft.NetApp.AvsDataStore",
        "azure.mgmt.netapp.models.EnableSubvolumes": "Microsoft.NetApp.EnableSubvolumes",
        "azure.mgmt.netapp.models.VolumeLanguage": "Microsoft.NetApp.VolumeLanguage",
        "azure.mgmt.netapp.models.BackupType": "Microsoft.NetApp.BackupType",
        "azure.mgmt.netapp.models.VolumeBackupRelationshipStatus": "Microsoft.NetApp.VolumeBackupRelationshipStatus",
        "azure.mgmt.netapp.models.VolumeRestoreRelationshipStatus": "Microsoft.NetApp.VolumeRestoreRelationshipStatus",
        "azure.mgmt.netapp.models.Type": "Microsoft.NetApp.Type",
        "azure.mgmt.netapp.models.NetAppProvisioningState": "Microsoft.NetApp.NetAppProvisioningState",
        "azure.mgmt.netapp.models.CredentialsStatus": "Microsoft.NetApp.CredentialsStatus",
        "azure.mgmt.netapp.models.BucketPermissions": "Microsoft.NetApp.BucketPermissions",
        "azure.mgmt.netapp.models.BucketPatchPermissions": "Microsoft.NetApp.BucketPatchPermissions",
        "azure.mgmt.netapp.models.RegionStorageToNetworkProximity": "Microsoft.NetApp.RegionStorageToNetworkProximity",
        "azure.mgmt.netapp.models.ActiveDirectoryStatus": "Microsoft.NetApp.ActiveDirectoryStatus",
        "azure.mgmt.netapp.models.KeySource": "Microsoft.NetApp.KeySource",
        "azure.mgmt.netapp.models.KeyVaultStatus": "Microsoft.NetApp.KeyVaultStatus",
        "azure.mgmt.netapp.models.MultiAdStatus": "Microsoft.NetApp.MultiAdStatus",
        "azure.mgmt.netapp.models.ManagedServiceIdentityType": "Azure.ResourceManager.CommonTypes.ManagedServiceIdentityType",
        "azure.mgmt.netapp.models.QosType": "Microsoft.NetApp.QosType",
        "azure.mgmt.netapp.models.EncryptionType": "Microsoft.NetApp.EncryptionType",
        "azure.mgmt.netapp.models.InAvailabilityReasonType": "Microsoft.NetApp.InAvailabilityReasonType",
        "azure.mgmt.netapp.models.CheckNameResourceTypes": "Microsoft.NetApp.CheckNameResourceTypes",
        "azure.mgmt.netapp.models.CheckQuotaNameResourceTypes": "Microsoft.NetApp.CheckQuotaNameResourceTypes",
        "azure.mgmt.netapp.models.NetworkSiblingSetProvisioningState": "Microsoft.NetApp.NetworkSiblingSetProvisioningState",
        "azure.mgmt.netapp.operations.Operations.list": "Azure.ResourceManager.Legacy.Operations.list",
        "azure.mgmt.netapp.aio.operations.Operations.list": "Azure.ResourceManager.Legacy.Operations.list",
        "azure.mgmt.netapp.operations.NetAppResourceQuotaLimitsAccountOperations.get": "Microsoft.NetApp.NetAppResourceQuotaLimitsAccount.get",
        "azure.mgmt.netapp.aio.operations.NetAppResourceQuotaLimitsAccountOperations.get": "Microsoft.NetApp.NetAppResourceQuotaLimitsAccount.get",
        "azure.mgmt.netapp.operations.NetAppResourceQuotaLimitsAccountOperations.list": "Microsoft.NetApp.NetAppResourceQuotaLimitsAccount.list",
        "azure.mgmt.netapp.aio.operations.NetAppResourceQuotaLimitsAccountOperations.list": "Microsoft.NetApp.NetAppResourceQuotaLimitsAccount.list",
        "azure.mgmt.netapp.operations.VolumeGroupsOperations.get": "Microsoft.NetApp.VolumeGroups.get",
        "azure.mgmt.netapp.aio.operations.VolumeGroupsOperations.get": "Microsoft.NetApp.VolumeGroups.get",
        "azure.mgmt.netapp.operations.VolumeGroupsOperations.begin_create": "Microsoft.NetApp.VolumeGroups.create",
        "azure.mgmt.netapp.aio.operations.VolumeGroupsOperations.begin_create": "Microsoft.NetApp.VolumeGroups.create",
        "azure.mgmt.netapp.operations.VolumeGroupsOperations.begin_delete": "Microsoft.NetApp.VolumeGroups.delete",
        "azure.mgmt.netapp.aio.operations.VolumeGroupsOperations.begin_delete": "Microsoft.NetApp.VolumeGroups.delete",
        "azure.mgmt.netapp.operations.VolumeGroupsOperations.list_by_net_app_account": "Microsoft.NetApp.NetAppAccounts.listByNetAppAccount",
        "azure.mgmt.netapp.aio.operations.VolumeGroupsOperations.list_by_net_app_account": "Microsoft.NetApp.NetAppAccounts.listByNetAppAccount",
        "azure.mgmt.netapp.operations.BackupsOperations.get": "Microsoft.NetApp.Backups.get",
        "azure.mgmt.netapp.aio.operations.BackupsOperations.get": "Microsoft.NetApp.Backups.get",
        "azure.mgmt.netapp.operations.BackupsOperations.begin_create": "Microsoft.NetApp.Backups.create",
        "azure.mgmt.netapp.aio.operations.BackupsOperations.begin_create": "Microsoft.NetApp.Backups.create",
        "azure.mgmt.netapp.operations.BackupsOperations.begin_update": "Microsoft.NetApp.Backups.update",
        "azure.mgmt.netapp.aio.operations.BackupsOperations.begin_update": "Microsoft.NetApp.Backups.update",
        "azure.mgmt.netapp.operations.BackupsOperations.begin_delete": "Microsoft.NetApp.Backups.delete",
        "azure.mgmt.netapp.aio.operations.BackupsOperations.begin_delete": "Microsoft.NetApp.Backups.delete",
        "azure.mgmt.netapp.operations.BackupsOperations.list_by_vault": "Microsoft.NetApp.Backups.listByVault",
        "azure.mgmt.netapp.aio.operations.BackupsOperations.list_by_vault": "Microsoft.NetApp.Backups.listByVault",
        "azure.mgmt.netapp.operations.BackupsOperations.get_latest_status": "Microsoft.NetApp.Volumes.getLatestStatus",
        "azure.mgmt.netapp.aio.operations.BackupsOperations.get_latest_status": "Microsoft.NetApp.Volumes.getLatestStatus",
        "azure.mgmt.netapp.operations.BackupsOperations.get_volume_latest_restore_status": "Microsoft.NetApp.Volumes.getVolumeLatestRestoreStatus",
        "azure.mgmt.netapp.aio.operations.BackupsOperations.get_volume_latest_restore_status": "Microsoft.NetApp.Volumes.getVolumeLatestRestoreStatus",
        "azure.mgmt.netapp.operations.VolumesOperations.get": "Microsoft.NetApp.Volumes.get",
        "azure.mgmt.netapp.aio.operations.VolumesOperations.get": "Microsoft.NetApp.Volumes.get",
        "azure.mgmt.netapp.operations.VolumesOperations.begin_create_or_update": "Microsoft.NetApp.Volumes.createOrUpdate",
        "azure.mgmt.netapp.aio.operations.VolumesOperations.begin_create_or_update": "Microsoft.NetApp.Volumes.createOrUpdate",
        "azure.mgmt.netapp.operations.VolumesOperations.begin_update": "Microsoft.NetApp.Volumes.update",
        "azure.mgmt.netapp.aio.operations.VolumesOperations.begin_update": "Microsoft.NetApp.Volumes.update",
        "azure.mgmt.netapp.operations.VolumesOperations.begin_delete": "Microsoft.NetApp.Volumes.delete",
        "azure.mgmt.netapp.aio.operations.VolumesOperations.begin_delete": "Microsoft.NetApp.Volumes.delete",
        "azure.mgmt.netapp.operations.VolumesOperations.list": "Microsoft.NetApp.Volumes.list",
        "azure.mgmt.netapp.aio.operations.VolumesOperations.list": "Microsoft.NetApp.Volumes.list",
        "azure.mgmt.netapp.operations.VolumesOperations.begin_populate_availability_zone": "Microsoft.NetApp.Volumes.populateAvailabilityZone",
        "azure.mgmt.netapp.aio.operations.VolumesOperations.begin_populate_availability_zone": "Microsoft.NetApp.Volumes.populateAvailabilityZone",
        "azure.mgmt.netapp.operations.VolumesOperations.begin_revert": "Microsoft.NetApp.Volumes.revert",
        "azure.mgmt.netapp.aio.operations.VolumesOperations.begin_revert": "Microsoft.NetApp.Volumes.revert",
        "azure.mgmt.netapp.operations.VolumesOperations.begin_reset_cifs_password": "Microsoft.NetApp.Volumes.resetCifsPassword",
        "azure.mgmt.netapp.aio.operations.VolumesOperations.begin_reset_cifs_password": "Microsoft.NetApp.Volumes.resetCifsPassword",
        "azure.mgmt.netapp.operations.VolumesOperations.begin_split_clone_from_parent": "Microsoft.NetApp.Volumes.splitCloneFromParent",
        "azure.mgmt.netapp.aio.operations.VolumesOperations.begin_split_clone_from_parent": "Microsoft.NetApp.Volumes.splitCloneFromParent",
        "azure.mgmt.netapp.operations.VolumesOperations.begin_break_file_locks": "Microsoft.NetApp.Volumes.breakFileLocks",
        "azure.mgmt.netapp.aio.operations.VolumesOperations.begin_break_file_locks": "Microsoft.NetApp.Volumes.breakFileLocks",
        "azure.mgmt.netapp.operations.VolumesOperations.begin_list_get_group_id_list_for_ldap_user": "Microsoft.NetApp.Volumes.listGetGroupIdListForLdapUser",
        "azure.mgmt.netapp.aio.operations.VolumesOperations.begin_list_get_group_id_list_for_ldap_user": "Microsoft.NetApp.Volumes.listGetGroupIdListForLdapUser",
        "azure.mgmt.netapp.operations.VolumesOperations.begin_break_replication": "Microsoft.NetApp.Volumes.breakReplication",
        "azure.mgmt.netapp.aio.operations.VolumesOperations.begin_break_replication": "Microsoft.NetApp.Volumes.breakReplication",
        "azure.mgmt.netapp.operations.VolumesOperations.begin_reestablish_replication": "Microsoft.NetApp.Volumes.reestablishReplication",
        "azure.mgmt.netapp.aio.operations.VolumesOperations.begin_reestablish_replication": "Microsoft.NetApp.Volumes.reestablishReplication",
        "azure.mgmt.netapp.operations.VolumesOperations.replication_status": "Microsoft.NetApp.Volumes.replicationStatus",
        "azure.mgmt.netapp.aio.operations.VolumesOperations.replication_status": "Microsoft.NetApp.Volumes.replicationStatus",
        "azure.mgmt.netapp.operations.VolumesOperations.list_replications": "Microsoft.NetApp.Volumes.listReplications",
        "azure.mgmt.netapp.aio.operations.VolumesOperations.list_replications": "Microsoft.NetApp.Volumes.listReplications",
        "azure.mgmt.netapp.operations.VolumesOperations.begin_resync_replication": "Microsoft.NetApp.Volumes.resyncReplication",
        "azure.mgmt.netapp.aio.operations.VolumesOperations.begin_resync_replication": "Microsoft.NetApp.Volumes.resyncReplication",
        "azure.mgmt.netapp.operations.VolumesOperations.begin_delete_replication": "Microsoft.NetApp.Volumes.deleteReplication",
        "azure.mgmt.netapp.aio.operations.VolumesOperations.begin_delete_replication": "Microsoft.NetApp.Volumes.deleteReplication",
        "azure.mgmt.netapp.operations.VolumesOperations.begin_authorize_replication": "Microsoft.NetApp.Volumes.authorizeReplication",
        "azure.mgmt.netapp.aio.operations.VolumesOperations.begin_authorize_replication": "Microsoft.NetApp.Volumes.authorizeReplication",
        "azure.mgmt.netapp.operations.VolumesOperations.begin_re_initialize_replication": "Microsoft.NetApp.Volumes.reInitializeReplication",
        "azure.mgmt.netapp.aio.operations.VolumesOperations.begin_re_initialize_replication": "Microsoft.NetApp.Volumes.reInitializeReplication",
        "azure.mgmt.netapp.operations.VolumesOperations.begin_peer_external_cluster": "Microsoft.NetApp.Volumes.peerExternalCluster",
        "azure.mgmt.netapp.aio.operations.VolumesOperations.begin_peer_external_cluster": "Microsoft.NetApp.Volumes.peerExternalCluster",
        "azure.mgmt.netapp.operations.VolumesOperations.begin_authorize_external_replication": "Microsoft.NetApp.Volumes.authorizeExternalReplication",
        "azure.mgmt.netapp.aio.operations.VolumesOperations.begin_authorize_external_replication": "Microsoft.NetApp.Volumes.authorizeExternalReplication",
        "azure.mgmt.netapp.operations.VolumesOperations.begin_finalize_external_replication": "Microsoft.NetApp.Volumes.finalizeExternalReplication",
        "azure.mgmt.netapp.aio.operations.VolumesOperations.begin_finalize_external_replication": "Microsoft.NetApp.Volumes.finalizeExternalReplication",
        "azure.mgmt.netapp.operations.VolumesOperations.begin_perform_replication_transfer": "Microsoft.NetApp.Volumes.performReplicationTransfer",
        "azure.mgmt.netapp.aio.operations.VolumesOperations.begin_perform_replication_transfer": "Microsoft.NetApp.Volumes.performReplicationTransfer",
        "azure.mgmt.netapp.operations.VolumesOperations.begin_pool_change": "Microsoft.NetApp.Volumes.poolChange",
        "azure.mgmt.netapp.aio.operations.VolumesOperations.begin_pool_change": "Microsoft.NetApp.Volumes.poolChange",
        "azure.mgmt.netapp.operations.VolumesOperations.begin_relocate": "Microsoft.NetApp.Volumes.relocate",
        "azure.mgmt.netapp.aio.operations.VolumesOperations.begin_relocate": "Microsoft.NetApp.Volumes.relocate",
        "azure.mgmt.netapp.operations.VolumesOperations.begin_finalize_relocation": "Microsoft.NetApp.Volumes.finalizeRelocation",
        "azure.mgmt.netapp.aio.operations.VolumesOperations.begin_finalize_relocation": "Microsoft.NetApp.Volumes.finalizeRelocation",
        "azure.mgmt.netapp.operations.VolumesOperations.begin_revert_relocation": "Microsoft.NetApp.Volumes.revertRelocation",
        "azure.mgmt.netapp.aio.operations.VolumesOperations.begin_revert_relocation": "Microsoft.NetApp.Volumes.revertRelocation",
        "azure.mgmt.netapp.operations.VolumesOperations.begin_list_quota_report": "Microsoft.NetApp.Volumes.listQuotaReport",
        "azure.mgmt.netapp.aio.operations.VolumesOperations.begin_list_quota_report": "Microsoft.NetApp.Volumes.listQuotaReport",
        "azure.mgmt.netapp.operations.SnapshotsOperations.get": "Microsoft.NetApp.Snapshots.get",
        "azure.mgmt.netapp.aio.operations.SnapshotsOperations.get": "Microsoft.NetApp.Snapshots.get",
        "azure.mgmt.netapp.operations.SnapshotsOperations.begin_create": "Microsoft.NetApp.Snapshots.create",
        "azure.mgmt.netapp.aio.operations.SnapshotsOperations.begin_create": "Microsoft.NetApp.Snapshots.create",
        "azure.mgmt.netapp.operations.SnapshotsOperations.begin_update": "Microsoft.NetApp.Snapshots.update",
        "azure.mgmt.netapp.aio.operations.SnapshotsOperations.begin_update": "Microsoft.NetApp.Snapshots.update",
        "azure.mgmt.netapp.operations.SnapshotsOperations.begin_delete": "Microsoft.NetApp.Snapshots.delete",
        "azure.mgmt.netapp.aio.operations.SnapshotsOperations.begin_delete": "Microsoft.NetApp.Snapshots.delete",
        "azure.mgmt.netapp.operations.SnapshotsOperations.list": "Microsoft.NetApp.Snapshots.list",
        "azure.mgmt.netapp.aio.operations.SnapshotsOperations.list": "Microsoft.NetApp.Snapshots.list",
        "azure.mgmt.netapp.operations.SnapshotsOperations.begin_restore_files": "Microsoft.NetApp.Snapshots.restoreFiles",
        "azure.mgmt.netapp.aio.operations.SnapshotsOperations.begin_restore_files": "Microsoft.NetApp.Snapshots.restoreFiles",
        "azure.mgmt.netapp.operations.SnapshotPoliciesOperations.get": "Microsoft.NetApp.SnapshotPolicies.get",
        "azure.mgmt.netapp.aio.operations.SnapshotPoliciesOperations.get": "Microsoft.NetApp.SnapshotPolicies.get",
        "azure.mgmt.netapp.operations.SnapshotPoliciesOperations.create": "Microsoft.NetApp.SnapshotPolicies.create",
        "azure.mgmt.netapp.aio.operations.SnapshotPoliciesOperations.create": "Microsoft.NetApp.SnapshotPolicies.create",
        "azure.mgmt.netapp.operations.SnapshotPoliciesOperations.begin_update": "Microsoft.NetApp.SnapshotPolicies.update",
        "azure.mgmt.netapp.aio.operations.SnapshotPoliciesOperations.begin_update": "Microsoft.NetApp.SnapshotPolicies.update",
        "azure.mgmt.netapp.operations.SnapshotPoliciesOperations.begin_delete": "Microsoft.NetApp.SnapshotPolicies.delete",
        "azure.mgmt.netapp.aio.operations.SnapshotPoliciesOperations.begin_delete": "Microsoft.NetApp.SnapshotPolicies.delete",
        "azure.mgmt.netapp.operations.SnapshotPoliciesOperations.list": "Microsoft.NetApp.SnapshotPolicies.list",
        "azure.mgmt.netapp.aio.operations.SnapshotPoliciesOperations.list": "Microsoft.NetApp.SnapshotPolicies.list",
        "azure.mgmt.netapp.operations.SnapshotPoliciesOperations.list_volumes": "Microsoft.NetApp.SnapshotPolicies.listVolumes",
        "azure.mgmt.netapp.aio.operations.SnapshotPoliciesOperations.list_volumes": "Microsoft.NetApp.SnapshotPolicies.listVolumes",
        "azure.mgmt.netapp.operations.BackupPoliciesOperations.get": "Microsoft.NetApp.BackupPolicies.get",
        "azure.mgmt.netapp.aio.operations.BackupPoliciesOperations.get": "Microsoft.NetApp.BackupPolicies.get",
        "azure.mgmt.netapp.operations.BackupPoliciesOperations.begin_create": "Microsoft.NetApp.BackupPolicies.create",
        "azure.mgmt.netapp.aio.operations.BackupPoliciesOperations.begin_create": "Microsoft.NetApp.BackupPolicies.create",
        "azure.mgmt.netapp.operations.BackupPoliciesOperations.begin_update": "Microsoft.NetApp.BackupPolicies.update",
        "azure.mgmt.netapp.aio.operations.BackupPoliciesOperations.begin_update": "Microsoft.NetApp.BackupPolicies.update",
        "azure.mgmt.netapp.operations.BackupPoliciesOperations.begin_delete": "Microsoft.NetApp.BackupPolicies.delete",
        "azure.mgmt.netapp.aio.operations.BackupPoliciesOperations.begin_delete": "Microsoft.NetApp.BackupPolicies.delete",
        "azure.mgmt.netapp.operations.BackupPoliciesOperations.list": "Microsoft.NetApp.BackupPolicies.list",
        "azure.mgmt.netapp.aio.operations.BackupPoliciesOperations.list": "Microsoft.NetApp.BackupPolicies.list",
        "azure.mgmt.netapp.operations.VolumeQuotaRulesOperations.get": "Microsoft.NetApp.VolumeQuotaRules.get",
        "azure.mgmt.netapp.aio.operations.VolumeQuotaRulesOperations.get": "Microsoft.NetApp.VolumeQuotaRules.get",
        "azure.mgmt.netapp.operations.VolumeQuotaRulesOperations.begin_create": "Microsoft.NetApp.VolumeQuotaRules.create",
        "azure.mgmt.netapp.aio.operations.VolumeQuotaRulesOperations.begin_create": "Microsoft.NetApp.VolumeQuotaRules.create",
        "azure.mgmt.netapp.operations.VolumeQuotaRulesOperations.begin_update": "Microsoft.NetApp.VolumeQuotaRules.update",
        "azure.mgmt.netapp.aio.operations.VolumeQuotaRulesOperations.begin_update": "Microsoft.NetApp.VolumeQuotaRules.update",
        "azure.mgmt.netapp.operations.VolumeQuotaRulesOperations.begin_delete": "Microsoft.NetApp.VolumeQuotaRules.delete",
        "azure.mgmt.netapp.aio.operations.VolumeQuotaRulesOperations.begin_delete": "Microsoft.NetApp.VolumeQuotaRules.delete",
        "azure.mgmt.netapp.operations.VolumeQuotaRulesOperations.list_by_volume": "Microsoft.NetApp.VolumeQuotaRules.listByVolume",
        "azure.mgmt.netapp.aio.operations.VolumeQuotaRulesOperations.list_by_volume": "Microsoft.NetApp.VolumeQuotaRules.listByVolume",
        "azure.mgmt.netapp.operations.BackupVaultsOperations.get": "Microsoft.NetApp.BackupVaults.get",
        "azure.mgmt.netapp.aio.operations.BackupVaultsOperations.get": "Microsoft.NetApp.BackupVaults.get",
        "azure.mgmt.netapp.operations.BackupVaultsOperations.begin_create_or_update": "Microsoft.NetApp.BackupVaults.createOrUpdate",
        "azure.mgmt.netapp.aio.operations.BackupVaultsOperations.begin_create_or_update": "Microsoft.NetApp.BackupVaults.createOrUpdate",
        "azure.mgmt.netapp.operations.BackupVaultsOperations.begin_update": "Microsoft.NetApp.BackupVaults.update",
        "azure.mgmt.netapp.aio.operations.BackupVaultsOperations.begin_update": "Microsoft.NetApp.BackupVaults.update",
        "azure.mgmt.netapp.operations.BackupVaultsOperations.begin_delete": "Microsoft.NetApp.BackupVaults.delete",
        "azure.mgmt.netapp.aio.operations.BackupVaultsOperations.begin_delete": "Microsoft.NetApp.BackupVaults.delete",
        "azure.mgmt.netapp.operations.BackupVaultsOperations.list_by_net_app_account": "Microsoft.NetApp.BackupVaults.listByNetAppAccount",
        "azure.mgmt.netapp.aio.operations.BackupVaultsOperations.list_by_net_app_account": "Microsoft.NetApp.BackupVaults.listByNetAppAccount",
        "azure.mgmt.netapp.operations.BucketsOperations.get": "Microsoft.NetApp.Buckets.get",
        "azure.mgmt.netapp.aio.operations.BucketsOperations.get": "Microsoft.NetApp.Buckets.get",
        "azure.mgmt.netapp.operations.BucketsOperations.begin_create_or_update": "Microsoft.NetApp.Buckets.createOrUpdate",
        "azure.mgmt.netapp.aio.operations.BucketsOperations.begin_create_or_update": "Microsoft.NetApp.Buckets.createOrUpdate",
        "azure.mgmt.netapp.operations.BucketsOperations.begin_update": "Microsoft.NetApp.Buckets.update",
        "azure.mgmt.netapp.aio.operations.BucketsOperations.begin_update": "Microsoft.NetApp.Buckets.update",
        "azure.mgmt.netapp.operations.BucketsOperations.begin_delete": "Microsoft.NetApp.Buckets.delete",
        "azure.mgmt.netapp.aio.operations.BucketsOperations.begin_delete": "Microsoft.NetApp.Buckets.delete",
        "azure.mgmt.netapp.operations.BucketsOperations.list": "Microsoft.NetApp.Buckets.list",
        "azure.mgmt.netapp.aio.operations.BucketsOperations.list": "Microsoft.NetApp.Buckets.list",
        "azure.mgmt.netapp.operations.BucketsOperations.generate_credentials": "Microsoft.NetApp.Buckets.generateCredentials",
        "azure.mgmt.netapp.aio.operations.BucketsOperations.generate_credentials": "Microsoft.NetApp.Buckets.generateCredentials",
        "azure.mgmt.netapp.operations.NetAppResourceQuotaLimitsOperations.get": "Microsoft.NetApp.SubscriptionQuotaItems.get",
        "azure.mgmt.netapp.aio.operations.NetAppResourceQuotaLimitsOperations.get": "Microsoft.NetApp.SubscriptionQuotaItems.get",
        "azure.mgmt.netapp.operations.NetAppResourceQuotaLimitsOperations.list": "Microsoft.NetApp.SubscriptionQuotaItems.list",
        "azure.mgmt.netapp.aio.operations.NetAppResourceQuotaLimitsOperations.list": "Microsoft.NetApp.SubscriptionQuotaItems.list",
        "azure.mgmt.netapp.operations.NetAppResourceRegionInfosOperations.get": "Microsoft.NetApp.RegionInfoResources.get",
        "azure.mgmt.netapp.aio.operations.NetAppResourceRegionInfosOperations.get": "Microsoft.NetApp.RegionInfoResources.get",
        "azure.mgmt.netapp.operations.NetAppResourceRegionInfosOperations.list": "Microsoft.NetApp.RegionInfoResources.list",
        "azure.mgmt.netapp.aio.operations.NetAppResourceRegionInfosOperations.list": "Microsoft.NetApp.RegionInfoResources.list",
        "azure.mgmt.netapp.operations.AccountsOperations.get": "Microsoft.NetApp.NetAppAccounts.get",
        "azure.mgmt.netapp.aio.operations.AccountsOperations.get": "Microsoft.NetApp.NetAppAccounts.get",
        "azure.mgmt.netapp.operations.AccountsOperations.begin_create_or_update": "Microsoft.NetApp.NetAppAccounts.createOrUpdate",
        "azure.mgmt.netapp.aio.operations.AccountsOperations.begin_create_or_update": "Microsoft.NetApp.NetAppAccounts.createOrUpdate",
        "azure.mgmt.netapp.operations.AccountsOperations.begin_update": "Microsoft.NetApp.NetAppAccounts.update",
        "azure.mgmt.netapp.aio.operations.AccountsOperations.begin_update": "Microsoft.NetApp.NetAppAccounts.update",
        "azure.mgmt.netapp.operations.AccountsOperations.begin_delete": "Microsoft.NetApp.NetAppAccounts.delete",
        "azure.mgmt.netapp.aio.operations.AccountsOperations.begin_delete": "Microsoft.NetApp.NetAppAccounts.delete",
        "azure.mgmt.netapp.operations.AccountsOperations.list": "Microsoft.NetApp.NetAppAccounts.list",
        "azure.mgmt.netapp.aio.operations.AccountsOperations.list": "Microsoft.NetApp.NetAppAccounts.list",
        "azure.mgmt.netapp.operations.AccountsOperations.list_by_subscription": "Microsoft.NetApp.NetAppAccounts.listBySubscription",
        "azure.mgmt.netapp.aio.operations.AccountsOperations.list_by_subscription": "Microsoft.NetApp.NetAppAccounts.listBySubscription",
        "azure.mgmt.netapp.operations.AccountsOperations.begin_renew_credentials": "Microsoft.NetApp.NetAppAccounts.renewCredentials",
        "azure.mgmt.netapp.aio.operations.AccountsOperations.begin_renew_credentials": "Microsoft.NetApp.NetAppAccounts.renewCredentials",
        "azure.mgmt.netapp.operations.AccountsOperations.begin_transition_to_cmk": "Microsoft.NetApp.NetAppAccounts.transitionToCmk",
        "azure.mgmt.netapp.aio.operations.AccountsOperations.begin_transition_to_cmk": "Microsoft.NetApp.NetAppAccounts.transitionToCmk",
        "azure.mgmt.netapp.operations.AccountsOperations.begin_get_change_key_vault_information": "Microsoft.NetApp.NetAppAccounts.getChangeKeyVaultInformation",
        "azure.mgmt.netapp.aio.operations.AccountsOperations.begin_get_change_key_vault_information": "Microsoft.NetApp.NetAppAccounts.getChangeKeyVaultInformation",
        "azure.mgmt.netapp.operations.AccountsOperations.begin_change_key_vault": "Microsoft.NetApp.NetAppAccounts.changeKeyVault",
        "azure.mgmt.netapp.aio.operations.AccountsOperations.begin_change_key_vault": "Microsoft.NetApp.NetAppAccounts.changeKeyVault",
        "azure.mgmt.netapp.operations.BackupsUnderAccountOperations.begin_migrate_backups": "Microsoft.NetApp.NetAppAccounts.migrateBackups",
        "azure.mgmt.netapp.aio.operations.BackupsUnderAccountOperations.begin_migrate_backups": "Microsoft.NetApp.NetAppAccounts.migrateBackups",
        "azure.mgmt.netapp.operations.PoolsOperations.get": "Microsoft.NetApp.CapacityPools.get",
        "azure.mgmt.netapp.aio.operations.PoolsOperations.get": "Microsoft.NetApp.CapacityPools.get",
        "azure.mgmt.netapp.operations.PoolsOperations.begin_create_or_update": "Microsoft.NetApp.CapacityPools.createOrUpdate",
        "azure.mgmt.netapp.aio.operations.PoolsOperations.begin_create_or_update": "Microsoft.NetApp.CapacityPools.createOrUpdate",
        "azure.mgmt.netapp.operations.PoolsOperations.begin_update": "Microsoft.NetApp.CapacityPools.update",
        "azure.mgmt.netapp.aio.operations.PoolsOperations.begin_update": "Microsoft.NetApp.CapacityPools.update",
        "azure.mgmt.netapp.operations.PoolsOperations.begin_delete": "Microsoft.NetApp.CapacityPools.delete",
        "azure.mgmt.netapp.aio.operations.PoolsOperations.begin_delete": "Microsoft.NetApp.CapacityPools.delete",
        "azure.mgmt.netapp.operations.PoolsOperations.list": "Microsoft.NetApp.CapacityPools.list",
        "azure.mgmt.netapp.aio.operations.PoolsOperations.list": "Microsoft.NetApp.CapacityPools.list",
        "azure.mgmt.netapp.operations.BackupsUnderBackupVaultOperations.begin_restore_files": "Microsoft.NetApp.Backups.restoreFiles",
        "azure.mgmt.netapp.aio.operations.BackupsUnderBackupVaultOperations.begin_restore_files": "Microsoft.NetApp.Backups.restoreFiles",
        "azure.mgmt.netapp.operations.BackupsUnderVolumeOperations.begin_migrate_backups": "Microsoft.NetApp.Volumes.migrateBackups",
        "azure.mgmt.netapp.aio.operations.BackupsUnderVolumeOperations.begin_migrate_backups": "Microsoft.NetApp.Volumes.migrateBackups",
        "azure.mgmt.netapp.operations.SubvolumesOperations.get": "Microsoft.NetApp.SubvolumeInfos.get",
        "azure.mgmt.netapp.aio.operations.SubvolumesOperations.get": "Microsoft.NetApp.SubvolumeInfos.get",
        "azure.mgmt.netapp.operations.SubvolumesOperations.begin_create": "Microsoft.NetApp.SubvolumeInfos.create",
        "azure.mgmt.netapp.aio.operations.SubvolumesOperations.begin_create": "Microsoft.NetApp.SubvolumeInfos.create",
        "azure.mgmt.netapp.operations.SubvolumesOperations.begin_update": "Microsoft.NetApp.SubvolumeInfos.update",
        "azure.mgmt.netapp.aio.operations.SubvolumesOperations.begin_update": "Microsoft.NetApp.SubvolumeInfos.update",
        "azure.mgmt.netapp.operations.SubvolumesOperations.begin_delete": "Microsoft.NetApp.SubvolumeInfos.delete",
        "azure.mgmt.netapp.aio.operations.SubvolumesOperations.begin_delete": "Microsoft.NetApp.SubvolumeInfos.delete",
        "azure.mgmt.netapp.operations.SubvolumesOperations.list_by_volume": "Microsoft.NetApp.SubvolumeInfos.listByVolume",
        "azure.mgmt.netapp.aio.operations.SubvolumesOperations.list_by_volume": "Microsoft.NetApp.SubvolumeInfos.listByVolume",
        "azure.mgmt.netapp.operations.SubvolumesOperations.begin_get_metadata": "Microsoft.NetApp.SubvolumeInfos.getMetadata",
        "azure.mgmt.netapp.aio.operations.SubvolumesOperations.begin_get_metadata": "Microsoft.NetApp.SubvolumeInfos.getMetadata",
        "azure.mgmt.netapp.operations.NetAppResourceOperations.check_name_availability": "Microsoft.NetApp.NetAppResourceOperationGroup.checkNameAvailability",
        "azure.mgmt.netapp.aio.operations.NetAppResourceOperations.check_name_availability": "Microsoft.NetApp.NetAppResourceOperationGroup.checkNameAvailability",
        "azure.mgmt.netapp.operations.NetAppResourceOperations.check_file_path_availability": "Microsoft.NetApp.NetAppResourceOperationGroup.checkFilePathAvailability",
        "azure.mgmt.netapp.aio.operations.NetAppResourceOperations.check_file_path_availability": "Microsoft.NetApp.NetAppResourceOperationGroup.checkFilePathAvailability",
        "azure.mgmt.netapp.operations.NetAppResourceOperations.check_quota_availability": "Microsoft.NetApp.NetAppResourceOperationGroup.checkQuotaAvailability",
        "azure.mgmt.netapp.aio.operations.NetAppResourceOperations.check_quota_availability": "Microsoft.NetApp.NetAppResourceOperationGroup.checkQuotaAvailability",
        "azure.mgmt.netapp.operations.NetAppResourceOperations.query_region_info": "Microsoft.NetApp.NetAppResourceOperationGroup.queryRegionInfo",
        "azure.mgmt.netapp.aio.operations.NetAppResourceOperations.query_region_info": "Microsoft.NetApp.NetAppResourceOperationGroup.queryRegionInfo",
        "azure.mgmt.netapp.operations.NetAppResourceOperations.query_network_sibling_set": "Microsoft.NetApp.NetAppResourceOperationGroup.queryNetworkSiblingSet",
        "azure.mgmt.netapp.aio.operations.NetAppResourceOperations.query_network_sibling_set": "Microsoft.NetApp.NetAppResourceOperationGroup.queryNetworkSiblingSet",
        "azure.mgmt.netapp.operations.NetAppResourceOperations.begin_update_network_sibling_set": "Microsoft.NetApp.NetAppResourceOperationGroup.updateNetworkSiblingSet",
        "azure.mgmt.netapp.aio.operations.NetAppResourceOperations.begin_update_network_sibling_set": "Microsoft.NetApp.NetAppResourceOperationGroup.updateNetworkSiblingSet",
        "azure.mgmt.netapp.operations.NetAppResourceUsagesOperations.list": "Microsoft.NetApp.NetAppResourceUsagesOperationGroup.list",
        "azure.mgmt.netapp.aio.operations.NetAppResourceUsagesOperations.list": "Microsoft.NetApp.NetAppResourceUsagesOperationGroup.list",
        "azure.mgmt.netapp.operations.NetAppResourceUsagesOperations.get": "Microsoft.NetApp.NetAppResourceUsagesOperationGroup.get",
        "azure.mgmt.netapp.aio.operations.NetAppResourceUsagesOperations.get": "Microsoft.NetApp.NetAppResourceUsagesOperationGroup.get"
    }
}