{
    "CrossLanguagePackageId": "Language.QuestionAnswering.Authoring",
    "CrossLanguageDefinitionId": {
        "azure.ai.language.questionanswering.authoring.models.ActiveLearningFeedback": "Language.QuestionAnswering.Authoring.ActiveLearningFeedback",
        "azure.ai.language.questionanswering.authoring.models.Assets": "Language.QuestionAnswering.Authoring.Assets",
        "azure.ai.language.questionanswering.authoring.models.Error": "Language.QuestionAnswering.Authoring.Error",
        "azure.ai.language.questionanswering.authoring.models.ErrorResponse": "Language.QuestionAnswering.Authoring.ErrorResponse",
        "azure.ai.language.questionanswering.authoring.models.FeedbackRecord": "Language.QuestionAnswering.Authoring.FeedbackRecord",
        "azure.ai.language.questionanswering.authoring.models.ImportFiles": "Language.QuestionAnswering.Authoring.ImportFiles",
        "azure.ai.language.questionanswering.authoring.models.ImportJobOptions": "Language.QuestionAnswering.Authoring.ImportJobOptions",
        "azure.ai.language.questionanswering.authoring.models.ImportQnaRecord": "Language.QuestionAnswering.Authoring.ImportQnaRecord",
        "azure.ai.language.questionanswering.authoring.models.InnerErrorModel": "Language.QuestionAnswering.Authoring.InnerErrorModel",
        "azure.ai.language.questionanswering.authoring.models.ProjectDeployment": "Language.QuestionAnswering.Authoring.ProjectDeployment",
        "azure.ai.language.questionanswering.authoring.models.ProjectSettings": "Language.QuestionAnswering.Authoring.ProjectSettings",
        "azure.ai.language.questionanswering.authoring.models.QnaDialog": "Language.QuestionAnswering.Authoring.QnaDialog",
        "azure.ai.language.questionanswering.authoring.models.QnaPrompt": "Language.QuestionAnswering.Authoring.QnaPrompt",
        "azure.ai.language.questionanswering.authoring.models.QnaRecord": "Language.QuestionAnswering.Authoring.QnaRecord",
        "azure.ai.language.questionanswering.authoring.models.QnaSourceRecord": "Language.QuestionAnswering.Authoring.QnaSourceRecord",
        "azure.ai.language.questionanswering.authoring.models.QuestionAnsweringAuthoringExportJobState": "Language.QuestionAnswering.Authoring.QuestionAnsweringAuthoringExportJobState",
        "azure.ai.language.questionanswering.authoring.models.QuestionAnsweringAuthoringImportJobState": "Language.QuestionAnswering.Authoring.QuestionAnsweringAuthoringImportJobState",
        "azure.ai.language.questionanswering.authoring.models.QuestionAnsweringAuthoringProjectDeletionJobState": "Language.QuestionAnswering.Authoring.QuestionAnsweringAuthoringProjectDeletionJobState",
        "azure.ai.language.questionanswering.authoring.models.QuestionAnsweringAuthoringProjectDeploymentJobState": "Language.QuestionAnswering.Authoring.QuestionAnsweringAuthoringProjectDeploymentJobState",
        "azure.ai.language.questionanswering.authoring.models.QuestionAnsweringAuthoringUpdateQnasJobState": "Language.QuestionAnswering.Authoring.QuestionAnsweringAuthoringUpdateQnasJobState",
        "azure.ai.language.questionanswering.authoring.models.QuestionAnsweringAuthoringUpdateSourcesJobState": "Language.QuestionAnswering.Authoring.QuestionAnsweringAuthoringUpdateSourcesJobState",
        "azure.ai.language.questionanswering.authoring.models.QuestionAnsweringProject": "Language.QuestionAnswering.Authoring.QuestionAnsweringProjectMetadata",
        "azure.ai.language.questionanswering.authoring.models.RetrieveQnaRecord": "Language.QuestionAnswering.Authoring.RetrieveQnaRecord",
        "azure.ai.language.questionanswering.authoring.models.SuggestedQuestion": "Language.QuestionAnswering.Authoring.SuggestedQuestion",
        "azure.ai.language.questionanswering.authoring.models.SuggestedQuestionsCluster": "Language.QuestionAnswering.Authoring.SuggestedQuestionsCluster",
        "azure.ai.language.questionanswering.authoring.models.SynonymAssets": "Language.QuestionAnswering.Authoring.SynonymAssets",
        "azure.ai.language.questionanswering.authoring.models.UpdateQnaRecord": "Language.QuestionAnswering.Authoring.UpdateQnaRecord",
        "azure.ai.language.questionanswering.authoring.models.UpdateQnaSourceRecord": "Language.QuestionAnswering.Authoring.UpdateQnaSourceRecord",
        "azure.ai.language.questionanswering.authoring.models.UpdateSourceFiles": "Language.QuestionAnswering.Authoring.UpdateSourceFiles",
        "azure.ai.language.questionanswering.authoring.models.UpdateSourceFromFileOperationRecord": "Language.QuestionAnswering.Authoring.UpdateSourceFromFileOperationRecord",
        "azure.ai.language.questionanswering.authoring.models.UpdateSourceRecord": "Language.QuestionAnswering.Authoring.UpdateSourceRecord",
        "azure.ai.language.questionanswering.authoring.models.WordAlterations": "Language.QuestionAnswering.Authoring.WordAlterations",
        "azure.ai.language.questionanswering.authoring.models.ErrorCode": "Language.QuestionAnswering.Authoring.ErrorCode",
        "azure.ai.language.questionanswering.authoring.models.InnerErrorCode": "Language.QuestionAnswering.Authoring.InnerErrorCode",
        "azure.ai.language.questionanswering.authoring.models.JobStatus": "Language.QuestionAnswering.Authoring.jobStatus",
        "azure.ai.language.questionanswering.authoring.models.Format": "Language.QuestionAnswering.Authoring.format",
        "azure.ai.language.questionanswering.authoring.models.AssetKind": "Language.QuestionAnswering.Authoring.AssestKind",
        "azure.ai.language.questionanswering.authoring.models.SourceKind": "Language.QuestionAnswering.Authoring.sourceKind",
        "azure.ai.language.questionanswering.authoring.models.SourceContentStructureKind": "Language.QuestionAnswering.Authoring.sourceContentStructureKind",
        "azure.ai.language.questionanswering.authoring.models.UpdateOperationKind": "Language.QuestionAnswering.Authoring.updateOperationKind",
        "azure.ai.language.questionanswering.authoring.QuestionAnsweringAuthoringClient.list_projects": "Language.QuestionAnsweringAuthoringClientCustomizations.QuestionAnsweringAuthoringClientOperations.listProjects",
        "azure.ai.language.questionanswering.authoring.aio.QuestionAnsweringAuthoringClient.list_projects": "Language.QuestionAnsweringAuthoringClientCustomizations.QuestionAnsweringAuthoringClientOperations.listProjects",
        "azure.ai.language.questionanswering.authoring.QuestionAnsweringAuthoringClient.get_project_details": "Language.QuestionAnsweringAuthoringClientCustomizations.QuestionAnsweringAuthoringClientOperations.getProjectDetails",
        "azure.ai.language.questionanswering.authoring.aio.QuestionAnsweringAuthoringClient.get_project_details": "Language.QuestionAnsweringAuthoringClientCustomizations.QuestionAnsweringAuthoringClientOperations.getProjectDetails",
        "azure.ai.language.questionanswering.authoring.QuestionAnsweringAuthoringClient.create_project": "Language.QuestionAnsweringAuthoringClientCustomizations.QuestionAnsweringAuthoringClientOperations.createProject",
        "azure.ai.language.questionanswering.authoring.aio.QuestionAnsweringAuthoringClient.create_project": "Language.QuestionAnsweringAuthoringClientCustomizations.QuestionAnsweringAuthoringClientOperations.createProject",
        "azure.ai.language.questionanswering.authoring.QuestionAnsweringAuthoringClient.begin_delete_project": "Language.QuestionAnsweringAuthoringClientCustomizations.QuestionAnsweringAuthoringClientOperations.deleteProject",
        "azure.ai.language.questionanswering.authoring.aio.QuestionAnsweringAuthoringClient.begin_delete_project": "Language.QuestionAnsweringAuthoringClientCustomizations.QuestionAnsweringAuthoringClientOperations.deleteProject",
        "azure.ai.language.questionanswering.authoring.QuestionAnsweringAuthoringClient.begin_export": "Language.QuestionAnsweringAuthoringClientCustomizations.QuestionAnsweringAuthoringClientOperations.export",
        "azure.ai.language.questionanswering.authoring.aio.QuestionAnsweringAuthoringClient.begin_export": "Language.QuestionAnsweringAuthoringClientCustomizations.QuestionAnsweringAuthoringClientOperations.export",
        "azure.ai.language.questionanswering.authoring.QuestionAnsweringAuthoringClient.begin_import_assets": "Language.QuestionAnsweringAuthoringClientCustomizations.QuestionAnsweringAuthoringClientOperations.import",
        "azure.ai.language.questionanswering.authoring.aio.QuestionAnsweringAuthoringClient.begin_import_assets": "Language.QuestionAnsweringAuthoringClientCustomizations.QuestionAnsweringAuthoringClientOperations.import",
        "azure.ai.language.questionanswering.authoring.QuestionAnsweringAuthoringClient.begin_import_from_files": "Language.QuestionAnsweringAuthoringClientCustomizations.QuestionAnsweringAuthoringClientOperations.importFromFiles",
        "azure.ai.language.questionanswering.authoring.aio.QuestionAnsweringAuthoringClient.begin_import_from_files": "Language.QuestionAnsweringAuthoringClientCustomizations.QuestionAnsweringAuthoringClientOperations.importFromFiles",
        "azure.ai.language.questionanswering.authoring.QuestionAnsweringAuthoringClient.begin_deploy_project": "Language.QuestionAnsweringAuthoringClientCustomizations.QuestionAnsweringAuthoringClientOperations.deployProject",
        "azure.ai.language.questionanswering.authoring.aio.QuestionAnsweringAuthoringClient.begin_deploy_project": "Language.QuestionAnsweringAuthoringClientCustomizations.QuestionAnsweringAuthoringClientOperations.deployProject",
        "azure.ai.language.questionanswering.authoring.QuestionAnsweringAuthoringClient.list_deployments": "Language.QuestionAnsweringAuthoringClientCustomizations.QuestionAnsweringAuthoringClientOperations.listDeployments",
        "azure.ai.language.questionanswering.authoring.aio.QuestionAnsweringAuthoringClient.list_deployments": "Language.QuestionAnsweringAuthoringClientCustomizations.QuestionAnsweringAuthoringClientOperations.listDeployments",
        "azure.ai.language.questionanswering.authoring.QuestionAnsweringAuthoringClient.list_synonyms": "Language.QuestionAnsweringAuthoringClientCustomizations.QuestionAnsweringAuthoringClientOperations.getSynonyms",
        "azure.ai.language.questionanswering.authoring.aio.QuestionAnsweringAuthoringClient.list_synonyms": "Language.QuestionAnsweringAuthoringClientCustomizations.QuestionAnsweringAuthoringClientOperations.getSynonyms",
        "azure.ai.language.questionanswering.authoring.QuestionAnsweringAuthoringClient.update_synonyms": "Language.QuestionAnsweringAuthoringClientCustomizations.QuestionAnsweringAuthoringClientOperations.updateSynonyms",
        "azure.ai.language.questionanswering.authoring.aio.QuestionAnsweringAuthoringClient.update_synonyms": "Language.QuestionAnsweringAuthoringClientCustomizations.QuestionAnsweringAuthoringClientOperations.updateSynonyms",
        "azure.ai.language.questionanswering.authoring.QuestionAnsweringAuthoringClient.list_sources": "Language.QuestionAnsweringAuthoringClientCustomizations.QuestionAnsweringAuthoringClientOperations.getSources",
        "azure.ai.language.questionanswering.authoring.aio.QuestionAnsweringAuthoringClient.list_sources": "Language.QuestionAnsweringAuthoringClientCustomizations.QuestionAnsweringAuthoringClientOperations.getSources",
        "azure.ai.language.questionanswering.authoring.QuestionAnsweringAuthoringClient.begin_update_sources": "Language.QuestionAnsweringAuthoringClientCustomizations.QuestionAnsweringAuthoringClientOperations.updateSources",
        "azure.ai.language.questionanswering.authoring.aio.QuestionAnsweringAuthoringClient.begin_update_sources": "Language.QuestionAnsweringAuthoringClientCustomizations.QuestionAnsweringAuthoringClientOperations.updateSources",
        "azure.ai.language.questionanswering.authoring.QuestionAnsweringAuthoringClient.begin_update_sources_from_files": "Language.QuestionAnsweringAuthoringClientCustomizations.QuestionAnsweringAuthoringClientOperations.updateSourcesFromFiles",
        "azure.ai.language.questionanswering.authoring.aio.QuestionAnsweringAuthoringClient.begin_update_sources_from_files": "Language.QuestionAnsweringAuthoringClientCustomizations.QuestionAnsweringAuthoringClientOperations.updateSourcesFromFiles",
        "azure.ai.language.questionanswering.authoring.QuestionAnsweringAuthoringClient.list_qnas": "Language.QuestionAnsweringAuthoringClientCustomizations.QuestionAnsweringAuthoringClientOperations.getQnas",
        "azure.ai.language.questionanswering.authoring.aio.QuestionAnsweringAuthoringClient.list_qnas": "Language.QuestionAnsweringAuthoringClientCustomizations.QuestionAnsweringAuthoringClientOperations.getQnas",
        "azure.ai.language.questionanswering.authoring.QuestionAnsweringAuthoringClient.begin_update_qnas": "Language.QuestionAnsweringAuthoringClientCustomizations.QuestionAnsweringAuthoringClientOperations.updateQnas",
        "azure.ai.language.questionanswering.authoring.aio.QuestionAnsweringAuthoringClient.begin_update_qnas": "Language.QuestionAnsweringAuthoringClientCustomizations.QuestionAnsweringAuthoringClientOperations.updateQnas",
        "azure.ai.language.questionanswering.authoring.QuestionAnsweringAuthoringClient.add_feedback": "Language.QuestionAnsweringAuthoringClientCustomizations.QuestionAnsweringAuthoringClientOperations.addFeedback",
        "azure.ai.language.questionanswering.authoring.aio.QuestionAnsweringAuthoringClient.add_feedback": "Language.QuestionAnsweringAuthoringClientCustomizations.QuestionAnsweringAuthoringClientOperations.addFeedback"
    }
}